dsmetapackage/__init__.py
dsmetapackage-0.1.0.dist-info/METADATA
dsmetapackage-0.1.0.dist-info/WHEEL
dsmetapackage-0.1.0.dist-info/RECORD
